[{"_id":"5a6edc71b8ae995110237b2a","email":"rahmeen","latitude":"26.8466937","longitude":"80.94616599999999","number":7,"__v":0},{"username":{"id":"5a6f2cc73062386844d5b5de","username":"sanju"},"_id":"5a6f32bde2f0550f84515dff","email":"sanju@gmail.com","latitude":"28.646559","longitude":"77.1145715","number":98898688,"__v":0},{"username":{"id":"5a706cbcc66f114ea86457e2","username":"abb"},"_id":"5a706cdec66f114ea86457e4","email":"a@bb.com","latitude":"28.613785999999998","longitude":"77.03846600000001","number":4,"__v":0},{"username":{"id":"5a706fd8106fbb36ac44b3d7","username":"rk"},"_id":"5a706fee106fbb36ac44b3d9","latitude":"28.613770100000004","longitude":"77.0384764","number":5,"__v":0},{"username":{"id":"5a7074397f4b943d248633a8","username":"gg"},"_id":"5a70747c7f4b943d248633aa","email":"gg","latitude":"28.6618976","longitude":"77.2273958","number":7,"__v":0},{"username":{"id":"5a7074bc9ef58c32a07a1080","username":"hj"},"_id":"5a7074d69ef58c32a07a1082","email":"hj","latitude":"28.6618976","longitude":"77.2273958","number":8,"__v":0},{"username":{"id":"5a7075dddd904048ac815ff6","username":"dd"},"_id":"5a7075f5dd904048ac815ff8","email":"dd","latitude":"28.613749000000002","longitude":"77.03848219999999","number":3,"__v":0},{"username":{"id":"5a707634dd904048ac815ff9","username":"uu"},"_id":"5a70764ddd904048ac815ffb","email":"uu","latitude":"28.613747300000004","longitude":"77.03848769999999","number":6,"__v":0},{"username":{"id":"5a708af2e90f4731dc1ade05","username":"rrrr"},"_id":"5a708b14e90f4731dc1ade07","email":"rrrr","latitude":"28.6137533","longitude":"77.0384813","number":6,"__v":0}]